bmstools/__init__.py
bmstools/_version.py
bmstools/jbd/__init__.py
bmstools/jbd/enums.py
bmstools/jbd/jbd.py
bmstools/jbd/logging.py
bmstools/jbd/parsers.py
bmstools/jbd/persist.py
bmstools/jbd/registers.py
bmstools-1.2.0.dist-info/LICENSE
bmstools-1.2.0.dist-info/METADATA
bmstools-1.2.0.dist-info/WHEEL
bmstools-1.2.0.dist-info/entry_points.txt
bmstools-1.2.0.dist-info/top_level.txt
bmstools-1.2.0.dist-info/RECORD
