Metadata-Version: 2.1
Name: bmstools
Version: 1.2.0
Summary: This package aims to provide open source tools for popular Battery Management Systems (BMS)
Home-page: https://gitlab.com/MrSurly/bms-tools.git
Author: Eric Poulsen
Author-email: "Eric Poulsen" <eric@zyxod.com>
Maintainer: Eric Poulsen
Maintainer-email: "Eric Poulsen" <eric@zyxod.com>
License: Creative Commons Attribution-Noncommercial-Share Alike license
Project-URL: Bug Tracker, https://gitlab.com/bms-tools/bms-tools/-/issues
Classifier: Programming Language :: Python :: 3
Classifier: License :: OSI Approved :: MIT License
Classifier: Operating System :: Microsoft :: Windows
Classifier: Operating System :: POSIX :: Linux
Requires-Python: >= 3.6
License-File: LICENSE
Requires-Dist: pyserial (~=3.4)
Requires-Dist: xlsxwriter (==1.3.7)
Provides-Extra: gui
Requires-Dist: wxPython (~=4.1.1) ; extra == 'gui'
Requires-Dist: pyinstaller ; extra == 'gui'
